umitools/__init__.py
umitools/est_err.py
umitools/find_hot_loci.py
umitools/reformat_umi_fastq.py
umitools/reformat_umi_sra_fastq.py
umitools/umi.py
umitools/umi_graph.py
umitools/umi_loci_with_duplicates.py
umitools/umi_mark_duplicates.py
umitools/umi_simulator.py
umitools/umitools.py
umitools/data/umitools.test.error_in_sra_umi_locator.fq.gz
umitools/data/umitools.test.r1.fq.gz
umitools/data/umitools.test.r2.fq.gz
umitools/data/umitools.test.small_rna.fq.gz
umitools-0.3.4.dist-info/DESCRIPTION.rst
umitools-0.3.4.dist-info/METADATA
umitools-0.3.4.dist-info/RECORD
umitools-0.3.4.dist-info/WHEEL
umitools-0.3.4.dist-info/entry_points.txt
umitools-0.3.4.dist-info/metadata.json
umitools-0.3.4.dist-info/top_level.txt
